odoo/addons/sale_invoice_split_payment/README.rst
odoo/addons/sale_invoice_split_payment/__init__.py
odoo/addons/sale_invoice_split_payment/__manifest__.py
odoo/addons/sale_invoice_split_payment/i18n/it.po
odoo/addons/sale_invoice_split_payment/i18n/sale_invoice_split_payment.pot
odoo/addons/sale_invoice_split_payment/models/__init__.py
odoo/addons/sale_invoice_split_payment/models/sale_order.py
odoo/addons/sale_invoice_split_payment/readme/CONTRIBUTORS.md
odoo/addons/sale_invoice_split_payment/readme/DESCRIPTION.md
odoo/addons/sale_invoice_split_payment/readme/USAGE.md
odoo/addons/sale_invoice_split_payment/static/description/icon.png
odoo/addons/sale_invoice_split_payment/static/description/index.html
odoo/addons/sale_invoice_split_payment/tests/__init__.py
odoo/addons/sale_invoice_split_payment/tests/test_sale_order.py
odoo_addon_sale_invoice_split_payment-18.0.1.0.0.4.dist-info/METADATA
odoo_addon_sale_invoice_split_payment-18.0.1.0.0.4.dist-info/WHEEL
odoo_addon_sale_invoice_split_payment-18.0.1.0.0.4.dist-info/top_level.txt
odoo_addon_sale_invoice_split_payment-18.0.1.0.0.4.dist-info/RECORD
